invenio_alma/__init__.py
invenio_alma/api.py
invenio_alma/cli.py
invenio_alma/click_param_type.py
invenio_alma/config.py
invenio_alma/decorators.py
invenio_alma/ext.py
invenio_alma/jobs.py
invenio_alma/proxies.py
invenio_alma/tasks.py
invenio_alma/utils.py
invenio_alma/views.py
invenio_alma/resources/__init__.py
invenio_alma/resources/config.py
invenio_alma/resources/resources.py
invenio_alma/services/__init__.py
invenio_alma/services/base.py
invenio_alma/services/config.py
invenio_alma/services/errors.py
invenio_alma/services/rest.py
invenio_alma/services/sru.py
invenio_alma/services/utils.py
invenio_alma-0.13.5.dist-info/licenses/AUTHORS.rst
invenio_alma-0.13.5.dist-info/licenses/LICENSE
invenio_alma-0.13.5.dist-info/METADATA
invenio_alma-0.13.5.dist-info/WHEEL
invenio_alma-0.13.5.dist-info/entry_points.txt
invenio_alma-0.13.5.dist-info/top_level.txt
invenio_alma-0.13.5.dist-info/RECORD
