Metadata-Version: 2.4
Name: invenio-alma
Version: 0.13.5
Summary: "Provides API for Alma."
Home-page: https://github.com/tu-graz-library/invenio-alma
Author: Graz University of Technology.
Author-email: info@inveniosoftware.org
License: MIT
Platform: any
Classifier: Development Status :: 5 - Production/Stable
Classifier: Programming Language :: Python :: 3.12
Classifier: Programming Language :: Python :: 3.13
Requires-Python: >=3.9
License-File: LICENSE
License-File: AUTHORS.rst
Requires-Dist: click>=7.0.0
Requires-Dist: click-option-group>=0.5.3
Requires-Dist: flask-resources>=1.2.0
Requires-Dist: invenio-access>=2.0.0
Requires-Dist: invenio-accounts>=3.0.0
Requires-Dist: invenio-jobs>=3.0.0
Requires-Dist: requests>=2.0.0
Provides-Extra: tests
Requires-Dist: invenio-app>=1.5.0; extra == "tests"
Requires-Dist: invenio-cache>=1.1.0; extra == "tests"
Requires-Dist: invenio-records-resources>=8.0.0; extra == "tests"
Requires-Dist: invenio-search[opensearch2]>=2.1.0; extra == "tests"
Requires-Dist: pytest-invenio>=1.4.3; extra == "tests"
Requires-Dist: pytest-black-ng>=0.4.0; extra == "tests"
Requires-Dist: ruff>=0.0.263; extra == "tests"
Requires-Dist: Sphinx>=4.2.0; extra == "tests"
Dynamic: license-file
